{
  "name": "Shopify",
  "slug": "shopify",
  "description": "Interact with Shopify Admin API for products, orders, customers, and store management.",
  "github_repo": "Shopify/dev-mcp",
  "category": "other",
  "official": true,
  "seo": {
    "title": "Shopify MCP Server (Official) — Install & Config",
    "meta_description": "Shopify MCP server: Interact with Shopify Admin API for products, orders, customers, and store management.. Install instructions, config snippet, and usage guide."
  }
}
