{
  "name": "HashiCorp Terraform",
  "slug": "hashicorp-terraform",
  "publisher": "HashiCorp",
  "description": "Syntax highlighting, IntelliSense, and validation for Terraform HCL files",
  "category": "devops",
  "installs": "8000000+",
  "vscode_id": "HashiCorp.terraform",
  "seo": {
    "title": "HashiCorp Terraform — VS Code Extension by HashiCorp",
    "meta_description": "HashiCorp Terraform: Syntax highlighting, IntelliSense, and validation for Terraform HCL files. Install in VS Code, features, and alternatives."
  }
}
