{
  "id": "COMP-0486",
  "slug": "3scale",
  "name": "3scale",
  "description": "3scale — Data Integration / ETL / Reverse ETL tool for developers",
  "website": "https://3scale.net",
  "logo": "https://logo.clearbit.com/3scale.net",
  "hq_country": "US",
  "status": "active",
  "categories": {
    "primary": {
      "id": "CAT-34",
      "slug": "data-integration-etl",
      "name": "Data Integration / ETL / Reverse ETL"
    },
    "secondary": []
  },
  "alternatives": [],
  "seo": {
    "title": "3scale Review 2026: Pricing, Alternatives & Lock-in Score",
    "meta_description": "Complete 3scale analysis: pricing, lock-in risk, migration difficulty. Compare with alternatives in Data Integration / ETL / Reverse ETL.",
    "keywords": [
      "3scale pricing",
      "3scale alternatives",
      "3scale review"
    ]
  },
  "updated_at": "2026-04-12T12:53:55.841Z",
  "created_at": "2026-04-12T12:53:55.841Z"
}
