{
  "id": "ast-grep",
  "slug": "ast-grep",
  "name": "ast-grep",
  "website": "https://ast-grep.github.io",
  "status": "active",
  "categories": {
    "primary": {
      "id": "CAT-37",
      "slug": "code-assistants",
      "name": "Code Assistants / Agent Tooling"
    }
  },
  "created_at": "2026-04-20T20:57:23.885Z",
  "updated_at": "2026-07-08T08:15:14.809Z",
  "logo": "https://www.google.com/s2/favicons?domain=ast-grep.github.io&sz=128",
  "description": "ast-grep — CLI tool for AST-based structural code search, linting, and rewriting across multiple languages.",
  "seo": {
    "title": "ast-grep — Code Assistants / Agent Tooling",
    "meta_description": "ast-grep: ast-grep — CLI tool for AST-based structural code search, linting, and rewriting across multiple languages."
  },
  "community": {
    "hn_mentions_30d": 1
  },
  "content": {
    "when_to_use": [
      "Searching code by structure rather than text patterns across repos",
      "Running AST-based lint rules for custom code style enforcement",
      "Automating large-scale structural refactors with rewrite rules",
      "Finding all usages of a code pattern across multi-language repos"
    ]
  },
  "review": {
    "pros": [
      "AST-based matching avoids regex false positives",
      "Fast Rust implementation scales to large monorepos",
      "Supports structural rewrites across many languages",
      "YAML rule files are readable and shareable"
    ],
    "cons": [
      "Pattern syntax has a real learning curve",
      "Language support varies in completeness",
      "Less IDE integration than semgrep or comby",
      "Debugging non-matching rules is frustrating"
    ],
    "verdict": "The best open-source structural search tool right now, worth the learning curve for any serious refactor.",
    "best_for": "Engineers doing codemods, lint rules, or codebase-wide refactors across languages",
    "not_for": "Users who just need simple text search or one-off find-and-replace"
  },
  "pricing": {
    "model": "free",
    "has_free_tier": true,
    "high_water_mark": false,
    "high_water_mark_reason": "free/open-source — no billing mechanism"
  },
  "scores": {
    "lock_in": {
      "level": "high",
      "score": 5,
      "reason": "OSS CLI, fully portable"
    },
    "transparency": {
      "level": "high",
      "score": 5,
      "reason": "Free open source"
    },
    "developer_experience": {
      "level": "high",
      "score": 5,
      "reason": "Solid docs with examples"
    }
  }
}
