{
  "id": "bult",
  "slug": "bult",
  "name": "Bult",
  "website": "https://bult.dev",
  "status": "active",
  "categories": {
    "primary": {
      "id": "CAT-36",
      "slug": "ai-api-sdk",
      "name": "AI API / SDK for Developers"
    },
    "secondary": [
      "ai-platform-other"
    ]
  },
  "created_at": "2026-04-20T20:57:23.889Z",
  "updated_at": "2026-07-10T19:18:34.419Z",
  "hq_country": "US",
  "logo": "https://www.google.com/s2/favicons?domain=bult.dev&sz=128",
  "description": "Bult — AI-assisted backend scaffolding tool for generating boilerplate code and API structures from specifications.",
  "seo": {
    "title": "Bult — AI API / SDK for Developers",
    "meta_description": "Bult: Bult — AI-assisted backend scaffolding tool for generating boilerplate code and API structures from specifications."
  },
  "community": {
    "hn_mentions_30d": 1285
  },
  "content": {
    "when_to_use": [
      "Automating repetitive developer tasks with AI agent workflows",
      "Building workflow automations triggered by code events",
      "Orchestrating multi-step AI pipelines for internal tooling",
      "Reducing context-switching with AI-assisted task management"
    ]
  },
  "review": {
    "pros": [
      "Generates backend scaffolds from specs",
      "Speeds up CRUD and API boilerplate",
      "Reduces cold-start friction on new services"
    ],
    "cons": [
      "Generated code still needs senior review",
      "Limited framework coverage",
      "Not a replacement for design work"
    ],
    "verdict": "Handy for early project scaffolding, but real architecture still belongs to humans.",
    "best_for": "Solo devs and small teams bootstrapping new backend services fast",
    "not_for": "Mature codebases with established patterns and style guides"
  },
  "pricing": {
    "model": "unknown",
    "has_free_tier": false,
    "high_water_mark": false,
    "high_water_mark_reason": "no explicit HWM evidence"
  },
  "scores": {
    "lock_in": {
      "level": "medium",
      "score": 3,
      "reason": "Scaffolding tool"
    },
    "transparency": {
      "level": "low",
      "score": 2,
      "reason": "Unknown pricing"
    },
    "developer_experience": {
      "level": "medium",
      "score": 3,
      "reason": "Early-stage scaffolder"
    }
  }
}
