{
  "id": "cangjie-lang",
  "slug": "cangjie-lang",
  "name": "Cangjie Programming Language",
  "website": "https://cangjie-lang.cn",
  "description": "Huaweis self-developed programming language (仓颉) for all-scenario application development on HarmonyOS.",
  "logo": "https://www.google.com/s2/favicons?domain=cangjie-lang.cn&sz=128",
  "status": "active",
  "categories": {
    "primary": {
      "id": "CAT-37",
      "slug": "code-assistants",
      "name": "Code Assistants / Agent Tooling"
    }
  },
  "created_at": "2026-04-20T21:33:16.793Z",
  "updated_at": "2026-04-21T01:21:14.933Z",
  "hq_country": "CN",
  "founded": 2024,
  "seo": {
    "title": "Cangjie Programming Language — Code Assistants / Agent Tooling",
    "meta_description": "Cangjie Programming Language: Huaweis self-developed programming language (仓颉) for all-scenario application development on HarmonyOS."
  },
  "community": {
    "hn_mentions_30d": 0
  },
  "content": {
    "when_to_use": [
      "Writing HarmonyOS applications with Huawei's native AI language",
      "Building cross-device apps targeting Huawei's ecosystem",
      "Integrating on-device AI features using Cangjie SDK",
      "Prototyping HarmonyOS widgets and services natively"
    ]
  },
  "review": {
    "pros": [
      "First-class language for HarmonyOS development",
      "Modern syntax combining concurrency, AI, and multi-paradigm features",
      "Backed by Huawei with long-term roadmap commitment",
      "Designed for all-scenario deployment including mobile and IoT"
    ],
    "cons": [
      "Ecosystem outside Huawei devices is essentially nonexistent",
      "Limited English tooling, docs, and community support",
      "Talent pool and hiring market are very small",
      "Lock-in to HarmonyOS limits portability"
    ],
    "verdict": "Only compelling if you are building for HarmonyOS; otherwise it is a strategic dead end for most developers.",
    "best_for": "Developers targeting HarmonyOS devices and Huawei ecosystem apps",
    "not_for": "Cross-platform projects or teams outside the Chinese device market"
  },
  "pricing": {
    "model": "free",
    "has_free_tier": true
  },
  "scores": {
    "lock_in": {
      "level": "high",
      "score": 2,
      "reason": "Proprietary Huawei language tied to HarmonyOS"
    },
    "transparency": {
      "level": "high",
      "score": 4,
      "reason": "Free to use, public info"
    },
    "developer_experience": {
      "level": "medium",
      "score": 3,
      "reason": "Emerging docs, mostly Chinese-language"
    }
  }
}
