{
  "id": "conduit",
  "slug": "conduit",
  "name": "Conduit",
  "website": "https://www.conduit.financial",
  "description": "Cross-border B2B payments platform using stablecoins to replace correspondent banking.",
  "logo": "https://logo.clearbit.com/conduit.financial",
  "status": "active",
  "categories": {
    "primary": {
      "id": "CAT-02",
      "slug": "payment-gateway",
      "name": "Payment Gateway / PSP"
    }
  },
  "created_at": "2026-04-20T21:33:16.814Z",
  "updated_at": "2026-04-20T21:33:16.814Z",
  "hq_country": "US",
  "founded": 2021,
  "seo": {
    "title": "Conduit — Payment Gateway / PSP | tool.news",
    "meta_description": "Conduit: Cross-border B2B payments platform using stablecoins to replace correspondent banking."
  }
}
