{
  "id": "COMP-0726",
  "slug": "contentful",
  "name": "Contentful",
  "description": "Contentful — No-code / Low-code App Builders tool for developers. Specializes in Headless CMS.",
  "website": "https://contentful.com",
  "logo": "https://www.google.com/s2/favicons?domain=contentful.com&sz=128",
  "hq_country": "Germany",
  "status": "active",
  "categories": {
    "primary": {
      "id": "CAT-42",
      "slug": "no-code-low-code",
      "name": "No-code / Low-code App Builders"
    },
    "secondary": []
  },
  "alternatives": [],
  "seo": {
    "title": "Contentful Review 2026: Pricing, Alternatives & Lock-in Score",
    "meta_description": "Complete Contentful analysis: pricing, lock-in risk, migration difficulty. Compare with alternatives in No-code / Low-code App Builders.",
    "keywords": [
      "contentful pricing",
      "contentful alternatives",
      "contentful review",
      "contentful vs",
      "no code low code"
    ]
  },
  "updated_at": "2026-04-15T11:22:09.610Z",
  "created_at": "2026-04-15T11:22:09.610Z",
  "content": {
    "when_to_use": [
      "Internal tools and dashboards",
      "Rapid prototyping",
      "Non-technical team workflows"
    ],
    "when_not_to_use": [
      "Complex custom applications",
      "High-performance systems"
    ],
    "consider_instead": [
      "backend-as-a-service"
    ]
  },
  "pricing": {
    "model": "freemium",
    "has_free_tier": true,
    "free_tier_limits": "free plan includes up to 10 users for the contentful platform",
    "entry_price": "$300 / month",
    "enterprise_available": true,
    "pricing_url": "https://contentful.com/pricing",
    "transparency_score": 5,
    "last_checked": "2026-04-15"
  }
}
