{
  "id": "COMP-0117",
  "slug": "cycode",
  "name": "Cycode",
  "description": "Cycode — Secrets Management tool for developers",
  "website": "https://cycode.com",
  "logo": "https://www.google.com/s2/favicons?domain=cycode.com&sz=128",
  "hq_country": "IL",
  "status": "active",
  "categories": {
    "primary": {
      "id": "CAT-08",
      "slug": "secrets-management",
      "name": "Secrets Management"
    },
    "secondary": [
      "CAT-31"
    ]
  },
  "alternatives": [],
  "seo": {
    "title": "Cycode Review 2026: Pricing, Alternatives & Lock-in Score",
    "meta_description": "Complete Cycode analysis: pricing, lock-in risk, migration difficulty. Compare with alternatives in Secrets Management.",
    "keywords": [
      "cycode pricing",
      "cycode alternatives",
      "cycode review"
    ]
  },
  "updated_at": "2026-04-15T07:26:16.868Z",
  "created_at": "2026-04-12T12:53:55.841Z",
  "content": {
    "when_to_use": [
      "Teams with many API keys/tokens",
      "CI/CD pipelines needing secure env vars",
      "SOC2/compliance requirements"
    ],
    "when_not_to_use": [
      "Solo developer with few secrets",
      "Static sites without backend"
    ],
    "consider_instead": [
      "identity-auth"
    ]
  },
  "community": {
    "hn_mentions_30d": 2
  },
  "pricing": {
    "model": "subscription",
    "has_free_tier": false,
    "entry_price": "$1",
    "enterprise_available": true,
    "pricing_url": "https://cycode.com/#pricing",
    "transparency_score": 4,
    "last_checked": "2026-04-15"
  }
}
