{
  "id": "COMP-1092",
  "slug": "duckdb",
  "name": "DuckDB",
  "description": "DuckDB — DBaaS / Serverless Databases tool for developers. Specializes in embedded analytics.",
  "website": "https://duckdb.org",
  "logo": "https://logo.clearbit.com/duckdb.org",
  "hq_country": "Netherlands",
  "status": "active",
  "categories": {
    "primary": {
      "id": "CAT-10",
      "slug": "dbaas",
      "name": "DBaaS / Serverless Databases"
    },
    "secondary": []
  },
  "alternatives": [],
  "seo": {
    "title": "DuckDB Review 2026: Pricing, Alternatives & Lock-in Score",
    "meta_description": "Complete DuckDB analysis: pricing, lock-in risk, migration difficulty. Compare with alternatives in DBaaS / Serverless Databases.",
    "keywords": [
      "duckdb pricing",
      "duckdb alternatives",
      "duckdb review",
      "duckdb vs",
      "dbaas"
    ]
  },
  "updated_at": "2026-04-17T12:55:27.572Z",
  "created_at": "2026-04-15T23:19:59.455Z",
  "content": {
    "when_to_use": [
      "Apps needing managed database",
      "Serverless architectures",
      "Global data distribution"
    ],
    "when_not_to_use": [
      "Simple key-value storage needs",
      "Embedded/offline-first apps"
    ],
    "consider_instead": [
      "backend-as-a-service"
    ]
  },
  "review": {
    "verdict": "Best for apps needing managed database. DuckDB offers custom pricing.",
    "pros": [
      "Apps needing managed database",
      "Serverless architectures",
      "Managed infrastructure removes ops overhead"
    ],
    "cons": [
      "Simple key-value storage needs",
      "Embedded/offline-first apps",
      "Storage and compute costs grow with data volume"
    ],
    "best_for": "Apps, Global",
    "not_for": "Simple, Offline projects"
  },
  "community": {
    "hn_mentions_30d": 33
  }
}
