{
  "id": "featurespace",
  "slug": "featurespace",
  "name": "Featurespace",
  "website": "https://featurespace.com",
  "status": "active",
  "categories": {
    "primary": {
      "id": "CAT-05",
      "slug": "fraud-risk-management",
      "name": "Fraud & Risk Management"
    }
  },
  "created_at": "2026-04-20T20:57:23.906Z",
  "updated_at": "2026-04-21T01:27:45.843Z",
  "hq_country": "UK",
  "logo": "https://logo.clearbit.com/featurespace.com",
  "description": "Featurespace — ARIC risk engine using adaptive behavioral analytics to detect fraud and financial crime in real-time transaction streams.",
  "seo": {
    "title": "Featurespace — Fraud & Risk Management",
    "meta_description": "Featurespace: Featurespace — ARIC risk engine using adaptive behavioral analytics to detect fraud and financial crime in real-time transaction streams."
  },
  "community": {
    "hn_mentions_30d": 0
  },
  "content": {
    "when_to_use": [
      "Adaptive behavioral analytics for real-time payment fraud",
      "Financial crime detection via ARIC risk engine for banks",
      "Account takeover scoring using behavioral sequence patterns",
      "Money laundering detection in cross-border payment flows",
      "Fraud model explainability for regulatory review compliance"
    ]
  },
  "review": {
    "pros": [
      "Adaptive behavioral analytics on live streams",
      "ARIC engine proven at tier-1 banks",
      "Handles card, ACH and real-time rails",
      "Strong explainability for model decisions"
    ],
    "cons": [
      "Enterprise deployment timelines in quarters",
      "On-prem footprint adds ops burden",
      "Pricing opaque and high six-figure minimums",
      "Overkill for non-financial fraud use cases"
    ],
    "verdict": "Top-shelf real-time fraud ML for banks and processors willing to invest in a long, deep integration.",
    "best_for": "Banks and payment processors running real-time fraud on card and faster-payment rails.",
    "not_for": "E-commerce or SaaS looking for a quick API with self-serve pricing."
  },
  "pricing": {
    "model": "custom",
    "has_free_tier": false
  },
  "scores": {
    "lock_in": {
      "level": "high",
      "score": 2,
      "reason": "ARIC engine deep in transaction flow"
    },
    "transparency": {
      "level": "low",
      "score": 1,
      "reason": "Custom enterprise pricing"
    },
    "developer_experience": {
      "level": "medium",
      "score": 3,
      "reason": "Enterprise fraud docs"
    }
  }
}
