{
  "id": "COMP-1458",
  "slug": "flipsite",
  "name": "Flipsite",
  "description": "Flipsite — CI/CD for Applications tool for developers. Specializes in Static Hosting.",
  "website": "https://flipsite.io",
  "logo": "https://www.google.com/s2/favicons?domain=flipsite.io&sz=128",
  "hq_country": "Finland",
  "status": "active",
  "categories": {
    "primary": {
      "id": "CAT-12",
      "slug": "cdn-edge",
      "name": "CDN / Edge / Acceleration"
    },
    "secondary": []
  },
  "alternatives": [],
  "seo": {
    "title": "Flipsite Review 2026: Pricing, Alternatives & Lock-in Score",
    "meta_description": "Complete Flipsite analysis: pricing, lock-in risk, migration difficulty. Compare with alternatives in CI/CD for Applications.",
    "keywords": [
      "flipsite pricing",
      "flipsite alternatives",
      "flipsite review",
      "flipsite vs",
      "ci cd"
    ]
  },
  "updated_at": "2026-05-31T08:46:17.066Z",
  "created_at": "2026-04-15T23:49:52.730Z",
  "content": {
    "when_to_use": [
      "Automated build/test/deploy pipelines",
      "Team collaboration on code",
      "Mobile app CI (iOS/Android)"
    ],
    "when_not_to_use": [
      "Manual deployment is sufficient",
      "Single-person hobby projects"
    ],
    "consider_instead": []
  },
  "review": {
    "verdict": "Best for automated build/test/deploy pipelines. Flipsite offers custom pricing.",
    "pros": [
      "Automated build/test/deploy pipelines",
      "Team collaboration on code",
      "Global edge network for low-latency delivery"
    ],
    "cons": [
      "Manual deployment is sufficient",
      "Single-person hobby projects",
      "Proprietary edge functions create platform dependency"
    ],
    "best_for": "Mobile",
    "not_for": "Hobby projects"
  },
  "community": {
    "hn_mentions_30d": 0
  },
  "pricing": {
    "model": "subscription",
    "has_free_tier": false,
    "high_water_mark": false,
    "high_water_mark_reason": "Monthly subscription; downgradable next cycle, no explicit peak-lock."
  },
  "scores": {
    "lock_in": {
      "level": "high",
      "score": 2,
      "reason": "Hosted site builder platform"
    },
    "transparency": {
      "level": "medium",
      "score": 3,
      "reason": "Subscription, partial public"
    },
    "developer_experience": {
      "level": "medium",
      "score": 3,
      "reason": "Site builder, limited DX"
    }
  }
}
