{
  "id": "go-feature-flag",
  "slug": "go-feature-flag",
  "name": "GO Feature Flag",
  "website": "https://gofeatureflag.org",
  "description": "Simple, complete and lightweight self-hosted feature flag solution, 100% open source. OpenFeature-native with 15+ language SDKs via relay proxy.",
  "logo": "https://www.google.com/s2/favicons?domain=gofeatureflag.org&sz=128",
  "status": "active",
  "categories": {
    "primary": {
      "id": "CAT-23",
      "slug": "feature-flags",
      "name": "Feature Flags / Remote Config"
    }
  },
  "created_at": "2026-04-20T21:33:16.855Z",
  "updated_at": "2026-04-30T08:13:07.543Z",
  "hq_country": "FR",
  "founded": 2020,
  "github": {
    "repo": "thomaspoignant/go-feature-flag",
    "stars": 2007,
    "open_issues": 37,
    "latest_release": "modules/core/v0.7.0",
    "release_date": "2026-04-29T12:19:40Z"
  },
  "seo": {
    "title": "GO Feature Flag — Feature Flags / Remote Config",
    "meta_description": "GO Feature Flag: Simple, complete and lightweight self-hosted feature flag solution, 100% open source. OpenFeature-native with 15+ language SDKs via relay proxy"
  },
  "community": {
    "hn_mentions_30d": 7
  },
  "health": {
    "bus_factor": 5,
    "last_commit_days_ago": 0,
    "release_frequency_days": 7,
    "open_issues": 35,
    "license": "MIT",
    "stars": 1995,
    "forks": 205,
    "updated_at": "2026-04-21",
    "health_score": "B"
  },
  "content": {
    "when_to_use": [
      "Self-hosted feature flags with 15+ language SDKs",
      "OpenFeature-native evaluation via relay proxy",
      "Flag definitions stored in Git, S3, or HTTP endpoints",
      "Zero-latency local evaluation without remote calls"
    ]
  },
  "review": {
    "pros": [
      "Self-hosted, 100% open source with generous features",
      "OpenFeature-native with 15+ language SDKs",
      "Flexible rules and rollout strategies",
      "Relay proxy simplifies multi-language setups"
    ],
    "cons": [
      "Config and ops are your responsibility",
      "UI less slick than SaaS alternatives",
      "Experimentation features are basic",
      "Scaling story needs planning at high QPS"
    ],
    "verdict": "One of the better OSS self-hosted flag options if you want OpenFeature compatibility without SaaS lock-in.",
    "best_for": "Engineering teams running flags in-house across many languages",
    "not_for": "Non-engineers wanting polished SaaS flag management"
  },
  "pricing": {
    "model": "free",
    "has_free_tier": true,
    "high_water_mark": false,
    "high_water_mark_reason": "Free/open-source — no commercial pricing, no HWM."
  },
  "scores": {
    "lock_in": {
      "level": "low",
      "score": 5,
      "reason": "OSS OpenFeature-native"
    },
    "transparency": {
      "level": "high",
      "score": 5,
      "reason": "Free OSS"
    },
    "developer_experience": {
      "level": "high",
      "score": 5,
      "reason": "15+ SDKs, great docs"
    }
  }
}
