{
  "id": "COMP-1018",
  "slug": "hud",
  "name": "Hud",
  "description": "Hud — Performance Monitoring / APM tool for developers. Specializes in application monitoring.",
  "website": "https://hud.io",
  "logo": "https://logo.clearbit.com/hud.io",
  "hq_country": "USA",
  "status": "active",
  "categories": {
    "primary": {
      "id": "CAT-21",
      "slug": "apm",
      "name": "Performance Monitoring / APM"
    },
    "secondary": []
  },
  "alternatives": [],
  "seo": {
    "title": "Hud Review 2026: Pricing, Alternatives & Lock-in Score",
    "meta_description": "Complete Hud analysis: pricing, lock-in risk, migration difficulty. Compare with alternatives in Performance Monitoring / APM.",
    "keywords": [
      "hud pricing",
      "hud alternatives",
      "hud review",
      "hud vs",
      "apm"
    ]
  },
  "updated_at": "2026-04-18T12:42:54.800Z",
  "created_at": "2026-04-15T23:19:59.455Z",
  "content": {
    "when_to_use": [
      "Microservices performance monitoring",
      "Distributed tracing",
      "Infrastructure monitoring at scale"
    ],
    "when_not_to_use": [
      "Simple monolith apps",
      "Static sites"
    ],
    "consider_instead": [
      "observability"
    ]
  },
  "review": {
    "verdict": "Hud is a Performance Monitoring / APM tool.",
    "pros": [
      "Pinpoints performance bottlenecks with distributed tracing"
    ],
    "cons": [
      "Per-host or per-seat pricing grows quickly with team size"
    ],
    "best_for": "Teams debugging latency and reliability issues",
    "not_for": "Simple scripts or batch jobs with no latency SLA"
  },
  "community": {
    "hn_mentions_30d": 561
  }
}
