{
  "id": "kushki",
  "slug": "kushki",
  "name": "Kushki",
  "website": "https://kushkipagos.com",
  "status": "active",
  "categories": {
    "primary": {
      "id": "CAT-02",
      "slug": "payment-gateway",
      "name": "Payment Gateway / PSP"
    }
  },
  "created_at": "2026-04-20T20:57:23.922Z",
  "updated_at": "2026-04-21T01:34:28.268Z",
  "hq_country": "EC",
  "logo": "https://logo.clearbit.com/kushkipagos.com",
  "scores": {
    "lock_in": {
      "level": "low",
      "score": 2,
      "data_portability": "api_only",
      "migration_complexity": "medium"
    }
  },
  "description": "Kushki — LatAm payment gateway focused on Colombia, Ecuador, Mexico, Chile, and Peru supporting cards and local bank rails.",
  "seo": {
    "title": "Kushki — Payment Gateway / PSP",
    "meta_description": "Kushki: Kushki — LatAm payment gateway focused on Colombia, Ecuador, Mexico, Chile, and Peru supporting cards and local bank rails."
  },
  "community": {
    "hn_mentions_30d": 1
  }
}
