{
  "id": "COMP-0210",
  "slug": "meilisearch",
  "name": "Meilisearch",
  "description": "Meilisearch — Search / Recommendations API tool for developers",
  "website": "https://meilisearch.com",
  "logo": "https://logo.clearbit.com/meilisearch.com",
  "hq_country": "FR",
  "status": "active",
  "categories": {
    "primary": {
      "id": "CAT-14",
      "slug": "search-recommendations",
      "name": "Search / Recommendations API"
    },
    "secondary": []
  },
  "alternatives": [],
  "seo": {
    "title": "Meilisearch Review 2026: Pricing, Alternatives & Lock-in Score",
    "meta_description": "Complete Meilisearch analysis: pricing, lock-in risk, migration difficulty. Compare with alternatives in Search / Recommendations API.",
    "keywords": [
      "meilisearch pricing",
      "meilisearch alternatives",
      "meilisearch review"
    ]
  },
  "updated_at": "2026-04-12T12:53:55.841Z",
  "created_at": "2026-04-12T12:53:55.841Z",
  "pricing": {
    "model": "hybrid",
    "has_free_tier": false,
    "entry_price": "$30/мес (Build, 50K searches)",
    "enterprise_available": true,
    "billing_complexity": "low",
    "transparency_score": 3,
    "last_checked": "2026-04-11",
    "pricing_url": "https://meilisearch.com/pricing"
  },
  "scores": {
    "lock_in": {
      "level": "low",
      "score": 1,
      "migration_complexity": "low",
      "data_portability": "Полный export",
      "api_compatibility": "Open-source API",
      "explanation": "Low — open-source, self-hosted"
    }
  },
  "scale": {
    "revenue": "unknown -- private, early stage",
    "data_status": "estimated"
  }
}
