{
  "id": "postfinance-api",
  "slug": "postfinance-api",
  "name": "PostFinance Developer",
  "website": "https://developer.postfinance.ch",
  "description": "Checkout API + Open Banking sandbox from Swiss Posts bank arm.",
  "logo": "https://ui-avatars.com/api/?name=PostFinance%20Developer&size=128&background=5E6AD2&color=fff&bold=true",
  "status": "active",
  "categories": {
    "primary": {
      "id": "CAT-02",
      "slug": "payment-gateway",
      "name": "Payment Gateway / PSP"
    }
  },
  "created_at": "2026-04-20T21:55:26.267Z",
  "updated_at": "2026-04-21T01:42:45.090Z",
  "hq_country": "CH",
  "seo": {
    "title": "PostFinance Developer — Payment Gateway / PSP",
    "meta_description": "PostFinance Developer: Checkout API + Open Banking sandbox from Swiss Posts bank arm."
  },
  "community": {
    "hn_mentions_30d": 0
  },
  "content": {
    "when_to_use": [
      "Checkout API integration for Swiss merchants accepting PostFinance",
      "Open Banking sandbox testing for Swiss fintech prototypes",
      "Bank account data retrieval via Swiss open banking endpoints"
    ]
  },
  "review": {
    "pros": [
      "Trusted Swiss bank infrastructure",
      "Checkout API plus Open Banking sandbox",
      "Strong local method coverage",
      "Regulatory trust in Switzerland"
    ],
    "cons": [
      "Switzerland-focused",
      "Docs partly German/French",
      "Slower iteration than fintech PSPs",
      "Enterprise-style onboarding"
    ],
    "verdict": "Solid for Swiss-native merchants needing bank-grade rails, but DX and pace trail modern PSPs.",
    "best_for": "Swiss merchants and fintechs needing a bank-backed checkout and Open Banking rails",
    "not_for": "Teams outside Switzerland or expecting fast iteration and English-first docs"
  },
  "pricing": {
    "model": "custom",
    "has_free_tier": false,
    "high_water_mark": false,
    "high_water_mark_reason": "No explicit peak-lock evidence; default FALSE per rules."
  },
  "scores": {
    "lock_in": {
      "level": "high",
      "score": 2,
      "reason": "Custom Swiss bank integration"
    },
    "transparency": {
      "level": "low",
      "score": 1,
      "reason": "Contact sales only"
    },
    "developer_experience": {
      "level": "medium",
      "score": 3,
      "reason": "Open banking sandbox available"
    }
  }
}
