{
  "id": "prescient-ai",
  "slug": "prescient-ai",
  "name": "Prescient AI",
  "website": "https://prescientai.com",
  "description": "Marketing mix modeling platform measuring halo effects, incrementality and cross-channel revenue impact without last-click bias.",
  "logo": "https://www.google.com/s2/favicons?domain=prescientai.com&sz=128",
  "status": "active",
  "categories": {
    "primary": {
      "id": "CAT-18",
      "slug": "mobile-attribution",
      "name": "Mobile Attribution / MMP"
    }
  },
  "created_at": "2026-04-20T21:33:16.863Z",
  "updated_at": "2026-04-22T19:23:43.700Z",
  "hq_country": "US",
  "founded": 2020,
  "seo": {
    "title": "Prescient AI — Mobile Attribution / MMP",
    "meta_description": "Prescient AI: Marketing mix modeling platform measuring halo effects, incrementality and cross-channel revenue impact without last-click bias."
  },
  "community": {
    "hn_mentions_30d": 8
  },
  "content": {
    "when_to_use": [
      "Measuring halo effects of brand campaigns with MMM",
      "Incrementality testing across channels without last-click bias",
      "Cross-channel revenue impact attribution for DTC brands"
    ]
  },
  "review": {
    "pros": [
      "Halo-effect and cross-channel revenue modeling",
      "Avoids last-click distortion in paid media",
      "Daily outputs for budget decisions",
      "Purpose-built for e-commerce brands"
    ],
    "cons": [
      "MMM, not deterministic attribution",
      "Requires decent spend to produce stable models",
      "Less useful for pure mobile app UA",
      "Black-box aspects require trust in vendor"
    ],
    "verdict": "Useful MMM alternative for DTC brands escaping last-click, but not a mobile install attribution tool.",
    "best_for": "DTC e-commerce brands wanting MMM-driven cross-channel allocation beyond last-click.",
    "not_for": "Mobile apps that need SKAN or deterministic install postbacks."
  },
  "pricing": {
    "model": "custom",
    "has_free_tier": false
  },
  "scores": {
    "lock_in": {
      "level": "high",
      "score": 2,
      "reason": "Custom MMM contracts"
    },
    "transparency": {
      "level": "low",
      "score": 1,
      "reason": "Contact sales only"
    },
    "developer_experience": {
      "level": "low",
      "score": 2,
      "reason": "Analytics platform, limited dev API"
    }
  }
}
