{
  "id": "rainforest-qa",
  "slug": "rainforest-qa",
  "name": "Rainforest QA",
  "website": "https://rainforestqa.com",
  "status": "active",
  "categories": {
    "primary": {
      "id": "CAT-26",
      "slug": "test-automation",
      "name": "Test Automation / Device Cloud"
    }
  },
  "created_at": "2026-04-20T20:57:23.939Z",
  "updated_at": "2026-04-21T01:44:14.833Z",
  "hq_country": "US",
  "logo": "https://www.google.com/s2/favicons?domain=rainforestqa.com&sz=128",
  "description": "Rainforest QA — QA-as-a-service platform combining AI and crowd testers for no-code E2E test creation and execution.",
  "seo": {
    "title": "Rainforest QA — Test Automation / Device Cloud",
    "meta_description": "Rainforest QA: Rainforest QA — QA-as-a-service platform combining AI and crowd testers for no-code E2E test creation and execution."
  },
  "community": {
    "hn_mentions_30d": 0
  },
  "content": {
    "when_to_use": [
      "QA-as-a-service with AI and crowd tester execution",
      "No-code E2E test creation via UI record and describe",
      "Parallel test execution across real QA testers",
      "Instant test maintenance by describing UI changes"
    ]
  },
  "review": {
    "pros": [
      "Combines AI with crowd testers on demand",
      "No-code E2E test creation for non-engineers",
      "Parallel execution speeds feedback",
      "Good for product teams without QA budget"
    ],
    "cons": [
      "Pricing is enterprise-level, not transparent",
      "Vendor-controlled test infrastructure",
      "Less flexible than code-based Playwright tests"
    ],
    "verdict": "Useful when you need QA coverage without hiring, but code-based tools win on maintainability and price.",
    "best_for": "Product teams without engineering QA capacity wanting outsourced coverage",
    "not_for": "Engineering orgs comfortable writing Playwright or Cypress tests in-house"
  },
  "pricing": {
    "model": "custom",
    "has_free_tier": false
  },
  "scores": {
    "lock_in": {
      "level": "high",
      "score": 2,
      "reason": "QA-as-a-service, tests hosted"
    },
    "transparency": {
      "level": "low",
      "score": 1,
      "reason": "Custom pricing, contact sales"
    },
    "developer_experience": {
      "level": "medium",
      "score": 3,
      "reason": "No-code E2E creation"
    }
  }
}
