{
  "id": "COMP-0789",
  "slug": "sazabi",
  "name": "Sazabi",
  "description": "Sazabi — Observability / Logging / Tracing tool for developers. Specializes in AI-Native Observability.",
  "website": "https://sazabi.io",
  "logo": "https://icons.duckduckgo.com/ip3/sazabi.io.ico",
  "hq_country": "US",
  "status": "active",
  "categories": {
    "primary": {
      "id": "CAT-22",
      "slug": "observability",
      "name": "Observability / Logging / Tracing"
    },
    "secondary": []
  },
  "alternatives": [],
  "seo": {
    "title": "Sazabi Review 2026: Pricing, Alternatives & Lock-in Score",
    "meta_description": "Complete Sazabi analysis: pricing, lock-in risk, migration difficulty. Compare with alternatives in Observability / Logging / Tracing.",
    "keywords": [
      "sazabi pricing",
      "sazabi alternatives",
      "sazabi review",
      "sazabi vs",
      "observability"
    ]
  },
  "updated_at": "2026-04-15T19:02:14.720Z",
  "created_at": "2026-04-15T11:22:09.610Z",
  "content": {
    "when_to_use": [
      "Distributed systems debugging",
      "Log aggregation and analysis",
      "OpenTelemetry-based monitoring"
    ],
    "when_not_to_use": [
      "Single-server apps with basic logging",
      "Non-technical teams"
    ],
    "consider_instead": [
      "apm"
    ]
  },
  "community": {
    "hn_mentions_30d": 1
  },
  "review": {
    "verdict": "Best for distributed systems debugging. Sazabi offers custom pricing.",
    "pros": [
      "Distributed systems debugging",
      "Log aggregation and analysis",
      "Centralized logs, metrics, and traces in one place"
    ],
    "cons": [
      "Single-server apps with basic logging",
      "Non-technical teams",
      "Data ingestion pricing can spike unexpectedly"
    ],
    "best_for": "Distributed systems debugging",
    "not_for": "Non-technical projects"
  }
}
