{
  "id": "yotascale",
  "slug": "yotascale",
  "name": "Yotascale",
  "website": "https://yotascale.com",
  "status": "active",
  "categories": {
    "primary": {
      "id": "CAT-12",
      "slug": "cdn-edge",
      "name": "CDN / Edge / Acceleration"
    }
  },
  "created_at": "2026-04-20T20:57:23.957Z",
  "updated_at": "2026-04-21T01:54:30.963Z",
  "hq_country": "US",
  "logo": "https://www.google.com/s2/favicons?domain=yotascale.com&sz=128",
  "description": "Yotascale — ML-driven cloud cost management with cost attribution, anomaly detection, and team showback.",
  "seo": {
    "title": "Yotascale — CDN / Edge / Acceleration",
    "meta_description": "Yotascale: Yotascale — ML-driven cloud cost management with cost attribution, anomaly detection, and team showback."
  },
  "community": {
    "hn_mentions_30d": 0
  },
  "content": {
    "when_to_use": [
      "ML-driven cloud cost attribution and anomaly detection",
      "Team-level showback and chargeback for multi-cloud spend",
      "Unit economics modeling: cost per customer or transaction",
      "FinOps intelligence replacing manual tagging and spreadsheets",
      "Real-time budget monitoring with automated Slack alerts"
    ]
  },
  "review": {
    "pros": [
      "ML-driven cost attribution tuned for engineering teams",
      "Strong anomaly detection with context",
      "Team-level showback with minimal tagging pain",
      "Good Kubernetes cost visibility"
    ],
    "cons": [
      "Smaller brand than CloudHealth or Apptio",
      "Enterprise pricing, no low-tier self-serve",
      "Heavier than needed for simple spend tracking",
      "Implementation time not trivial"
    ],
    "verdict": "Engineer-friendly cost attribution with sharp ML anomaly detection, mostly a fit for mid-to-large cloud spenders.",
    "best_for": "Engineering orgs with $1M+ monthly cloud spend wanting team-level attribution",
    "not_for": "Small teams happy with Vantage, Infracost, or native provider dashboards"
  },
  "pricing": {
    "model": "custom",
    "has_free_tier": false
  },
  "scores": {
    "lock_in": {
      "level": "medium",
      "score": 3,
      "reason": "Cloud cost data, exportable"
    },
    "transparency": {
      "level": "low",
      "score": 1,
      "reason": "Custom enterprise pricing"
    },
    "developer_experience": {
      "level": "medium",
      "score": 3,
      "reason": "Integrations, limited docs"
    }
  }
}
