{
  "id": "zenhub",
  "slug": "zenhub",
  "name": "Zenhub",
  "website": "https://zenhub.com",
  "status": "active",
  "categories": {
    "primary": {
      "id": "CAT-25",
      "slug": "ci-cd",
      "name": "CI/CD for Applications"
    }
  },
  "created_at": "2026-04-20T20:57:23.957Z",
  "updated_at": "2026-04-21T01:54:43.544Z",
  "hq_country": "CA",
  "founded": 2014,
  "logo": "https://www.google.com/s2/favicons?domain=zenhub.com&sz=128",
  "description": "Zenhub — GitHub-native project management tool with Kanban boards, sprints, and roadmaps embedded inside GitHub.",
  "seo": {
    "title": "Zenhub — CI/CD for Applications",
    "meta_description": "Zenhub: Zenhub — GitHub-native project management tool with Kanban boards, sprints, and roadmaps embedded inside GitHub."
  },
  "community": {
    "hn_mentions_30d": 0
  },
  "content": {
    "when_to_use": [
      "GitHub-native Kanban boards without leaving GitHub",
      "Sprint planning and velocity tracking inside GitHub",
      "Roadmap visualization linked to GitHub milestones",
      "Multi-repo Epics connecting issues across repositories"
    ]
  },
  "review": {
    "pros": [
      "Kanban and sprints embedded directly in GitHub issues",
      "Roadmaps and dependencies across repos",
      "Less context-switching than Jira",
      "Good reports tied to actual commit/PR data"
    ],
    "cons": [
      "Price climbs fast per seat",
      "Occasional sync issues with GitHub state",
      "Weaker for non-engineering teams than Linear or Jira",
      "Lock-in once the company leans on it"
    ],
    "verdict": "The strongest 'PM inside GitHub' tool, best when your whole org actually lives in GitHub issues.",
    "best_for": "Engineering-led orgs that want PM on top of GitHub without moving to Jira or Linear.",
    "not_for": "Orgs with heavy non-engineering PM needs or already standardized on Linear/Jira."
  },
  "pricing": {
    "model": "subscription",
    "has_free_tier": false,
    "high_water_mark": false,
    "high_water_mark_reason": "monthly subscription, downgradable"
  },
  "scores": {
    "lock_in": {
      "level": "medium",
      "score": 3,
      "reason": "GitHub-native, tied to GH"
    },
    "transparency": {
      "level": "high",
      "score": 5,
      "reason": "Public subscription pricing"
    },
    "developer_experience": {
      "level": "high",
      "score": 4,
      "reason": "GitHub integration, APIs"
    }
  }
}
